_ldap.cp313-win32.pyd

ldapurl.py

ldif.py

__pycache__/ldapurl.cpython-313.opt-1.pyc

__pycache__/ldif.cpython-313.opt-1.pyc

ldap/__init__.py

ldap/async.py

ldap/asyncsearch.py

ldap/cidict.py

ldap/compat.py

ldap/constants.py

ldap/dn.py

ldap/filter.py

ldap/functions.py

ldap/ldapobject.py

ldap/logger.py

ldap/modlist.py

ldap/pkginfo.py

ldap/resiter.py

ldap/sasl.py

ldap/syncrepl.py

ldap/__pycache__/__init__.cpython-313.opt-1.pyc

ldap/__pycache__/async.cpython-313.opt-1.pyc

ldap/__pycache__/asyncsearch.cpython-313.opt-1.pyc

ldap/__pycache__/cidict.cpython-313.opt-1.pyc

ldap/__pycache__/compat.cpython-313.opt-1.pyc

ldap/__pycache__/constants.cpython-313.opt-1.pyc

ldap/__pycache__/dn.cpython-313.opt-1.pyc

ldap/__pycache__/filter.cpython-313.opt-1.pyc

ldap/__pycache__/functions.cpython-313.opt-1.pyc

ldap/__pycache__/ldapobject.cpython-313.opt-1.pyc

ldap/__pycache__/logger.cpython-313.opt-1.pyc

ldap/__pycache__/modlist.cpython-313.opt-1.pyc

ldap/__pycache__/pkginfo.cpython-313.opt-1.pyc

ldap/__pycache__/resiter.cpython-313.opt-1.pyc

ldap/__pycache__/sasl.cpython-313.opt-1.pyc

ldap/__pycache__/syncrepl.cpython-313.opt-1.pyc

ldap/controls/__init__.py

ldap/controls/deref.py

ldap/controls/libldap.py

ldap/controls/openldap.py

ldap/controls/pagedresults.py

ldap/controls/ppolicy.py

ldap/controls/psearch.py

ldap/controls/pwdpolicy.py

ldap/controls/readentry.py

ldap/controls/sessiontrack.py

ldap/controls/simple.py

ldap/controls/sss.py

ldap/controls/vlv.py

ldap/controls/__pycache__/__init__.cpython-313.opt-1.pyc

ldap/controls/__pycache__/deref.cpython-313.opt-1.pyc

ldap/controls/__pycache__/libldap.cpython-313.opt-1.pyc

ldap/controls/__pycache__/openldap.cpython-313.opt-1.pyc

ldap/controls/__pycache__/pagedresults.cpython-313.opt-1.pyc

ldap/controls/__pycache__/ppolicy.cpython-313.opt-1.pyc

python_ldap_build_windows-3.4.4.dist-info/licenses/LICENCE
python_ldap_build_windows-3.4.4.dist-info/METADATA
python_ldap_build_windows-3.4.4.dist-info/WHEEL
python_ldap_build_windows-3.4.4.dist-info/top_level.txt
python_ldap_build_windows-3.4.4.dist-info/RECORD
