Metadata-Version: 2.4
Name: python-ldap-build-windows
Version: 3.4.4
Summary: Python modules for implementing LDAP clients
Home-page: https://www.python-ldap-build-windows.org/
Download-URL: https://pypi.org/project/python-ldap-build-windows/
Author: python-ldap-build-windows project
Author-email: python-ldap-build-windows@python.org
License: Python style
Classifier: Development Status :: 5 - Production/Stable
Classifier: Intended Audience :: Developers
Classifier: Intended Audience :: System Administrators
Classifier: Operating System :: OS Independent
Classifier: Operating System :: MacOS :: MacOS X
Classifier: Operating System :: Microsoft :: Windows
Classifier: Operating System :: POSIX
Classifier: Programming Language :: C
Classifier: Programming Language :: Python
Classifier: Programming Language :: Python :: 3
Classifier: Programming Language :: Python :: 3.6
Classifier: Programming Language :: Python :: 3.7
Classifier: Programming Language :: Python :: 3.8
Classifier: Programming Language :: Python :: 3.9
Classifier: Programming Language :: Python :: 3.10
Classifier: Programming Language :: Python :: 3.11
Classifier: Programming Language :: Python :: 3.12
Classifier: Topic :: Database
Classifier: Topic :: Internet
Classifier: Topic :: Software Development :: Libraries :: Python Modules
Classifier: Topic :: System :: Systems Administration :: Authentication/Directory :: LDAP
Classifier: License :: OSI Approved :: Python Software Foundation License
Requires-Python: >=3.6
License-File: LICENCE
Requires-Dist: pyasn1>=0.3.7
Requires-Dist: pyasn1_modules>=0.1.5
Dynamic: author
Dynamic: author-email
Dynamic: classifier
Dynamic: description
Dynamic: download-url
Dynamic: home-page
Dynamic: license
Dynamic: license-file
Dynamic: requires-dist
Dynamic: requires-python
Dynamic: summary
